kani/ext/multimodal_core/__init__.py
kani/ext/multimodal_core/_version.py
kani/ext/multimodal_core/audio.py
kani/ext/multimodal_core/base.py
kani/ext/multimodal_core/cli.py
kani/ext/multimodal_core/exceptions.py
kani/ext/multimodal_core/image.py
kani/ext/multimodal_core/types.py
kani/ext/multimodal_core/utils.py
kani/ext/multimodal_core/video.py
kani_multimodal_core-0.0.3.dist-info/METADATA
kani_multimodal_core-0.0.3.dist-info/WHEEL
kani_multimodal_core-0.0.3.dist-info/licenses/LICENSE
kani_multimodal_core-0.0.3.dist-info/RECORD
