Metadata-Version: 2.4
Name: kani-multimodal-core
Version: 0.0.3
Summary: Core shared libraries for multimodal Kani extensions.
Project-URL: Homepage, https://github.com/zhudotexe/kani-multimodal-core
Project-URL: Bug Tracker, https://github.com/zhudotexe/kani-multimodal-core/issues
Author-email: Andrew Zhu <andrew@zhu.codes>
License: MIT License
License-File: LICENSE
Classifier: Development Status :: 4 - Beta
Classifier: Intended Audience :: Science/Research
Classifier: License :: OSI Approved :: MIT License
Classifier: Operating System :: OS Independent
Classifier: Programming Language :: Python :: 3
Classifier: Topic :: Scientific/Engineering :: Artificial Intelligence
Requires-Python: >=3.10
Requires-Dist: aiohttp<4.0.0,>=3.0.0
Requires-Dist: audioop-lts>=0.2.1; python_version >= '3.13'
Requires-Dist: kani<2.0.0,>=1.6.0
Requires-Dist: numpy<3.0.0,>=2.0.0
Requires-Dist: pillow>=9.0.0
Requires-Dist: pydub<1.0.0,>=0.20.0
